Metadata-Version: 2.1
Name: torch-layer-normalization
Version: 0.11.0
Summary: Layer normalization implemented in PyTorch
Home-page: https://github.com/CyberZHG/torch-layer-normalization
Author: CyberZHG
Author-email: CyberZHG@users.noreply.github.com
License: MIT
Platform: UNKNOWN
Classifier: Programming Language :: Python :: 3
Classifier: License :: OSI Approved :: MIT License
Classifier: Operating System :: OS Independent
